setup.cfg
setup.py
xnm/__init__.py
xnm/__main__.py
xnm.egg-info/PKG-INFO
xnm.egg-info/SOURCES.txt
xnm.egg-info/dependency_links.txt
xnm.egg-info/requires.txt
xnm.egg-info/top_level.txt