Metadata-Version: 1.1
Name: xnm
Version: 0.1
Summary: lightweight GUi for NetworkManager written in Tkinter, with simple xmobar integration
Home-page: https://github.com/smcl/xnm
Author: Sean McLemon
Author-email: sean.mclemon@gmail.com
License: UNKNOWN
Download-URL: https://github.com/smcl/xnm/tarball/0.1
Keywords: NetworkManager,Network,wifi,xnm,xmonad,xmobar
Platform: UNKNOWN
